LICENSE
MANIFEST.in
README.rst
buildout.cfg
develop.cfg
pyproject.toml
requirements.txt
setup.py
version.txt
bob/__init__.py
bob.learn.mlp.egg-info/PKG-INFO
bob.learn.mlp.egg-info/SOURCES.txt
bob.learn.mlp.egg-info/dependency_links.txt
bob.learn.mlp.egg-info/entry_points.txt
bob.learn.mlp.egg-info/not-zip-safe
bob.learn.mlp.egg-info/requires.txt
bob.learn.mlp.egg-info/top_level.txt
bob/learn/__init__.py
bob/learn/mlp/__init__.py
bob/learn/mlp/backprop.cpp
bob/learn/mlp/cost.cpp
bob/learn/mlp/machine.cpp
bob/learn/mlp/main.cpp
bob/learn/mlp/roll.cpp
bob/learn/mlp/rprop.cpp
bob/learn/mlp/shuffler.cpp
bob/learn/mlp/test_backprop.py
bob/learn/mlp/test_cost.py
bob/learn/mlp/test_machine.py
bob/learn/mlp/test_roll.py
bob/learn/mlp/test_rprop.py
bob/learn/mlp/test_shuffler.py
bob/learn/mlp/test_utils.py
bob/learn/mlp/trainer.cpp
bob/learn/mlp/utils.h
bob/learn/mlp/version.cpp
bob/learn/mlp/cxx/backprop.cpp
bob/learn/mlp/cxx/cross_entropy.cpp
bob/learn/mlp/cxx/machine.cpp
bob/learn/mlp/cxx/roll.cpp
bob/learn/mlp/cxx/rprop.cpp
bob/learn/mlp/cxx/shuffler.cpp
bob/learn/mlp/cxx/square_error.cpp
bob/learn/mlp/cxx/trainer.cpp
bob/learn/mlp/include/bob.learn.mlp/api.h
bob/learn/mlp/include/bob.learn.mlp/backprop.h
bob/learn/mlp/include/bob.learn.mlp/config.h
bob/learn/mlp/include/bob.learn.mlp/cost.h
bob/learn/mlp/include/bob.learn.mlp/cross_entropy.h
bob/learn/mlp/include/bob.learn.mlp/machine.h
bob/learn/mlp/include/bob.learn.mlp/roll.h
bob/learn/mlp/include/bob.learn.mlp/rprop.h
bob/learn/mlp/include/bob.learn.mlp/shuffler.h
bob/learn/mlp/include/bob.learn.mlp/square_error.h
bob/learn/mlp/include/bob.learn.mlp/trainer.h
doc/c_cpp_api.rst
doc/conf.py
doc/guide.rst
doc/index.rst
doc/links.rst
doc/py_api.rst